FIAT/P0.py
FIAT/__init__.py
FIAT/argyris.py
FIAT/brezzi_douglas_fortin_marini.py
FIAT/brezzi_douglas_marini.py
FIAT/bubble.py
FIAT/crouzeix_raviart.py
FIAT/discontinuous.py
FIAT/discontinuous_lagrange.py
FIAT/discontinuous_raviart_thomas.py
FIAT/discontinuous_taylor.py
FIAT/dual_set.py
FIAT/enriched.py
FIAT/expansions.py
FIAT/finite_element.py
FIAT/functional.py
FIAT/gauss_legendre.py
FIAT/gauss_lobatto_legendre.py
FIAT/hdiv_trace.py
FIAT/hdivcurl.py
FIAT/hellan_herrmann_johnson.py
FIAT/hermite.py
FIAT/jacobi.py
FIAT/lagrange.py
FIAT/mixed.py
FIAT/morley.py
FIAT/nedelec.py
FIAT/nedelec_second_kind.py
FIAT/nodal_enriched.py
FIAT/orthopoly.py
FIAT/polynomial_set.py
FIAT/quadrature.py
FIAT/quadrature_element.py
FIAT/quadrature_schemes.py
FIAT/raviart_thomas.py
FIAT/reference_element.py
FIAT/regge.py
FIAT/restricted.py
FIAT/tensor_product.py
fenics_fiat-2018.1.0.dist-info/METADATA
fenics_fiat-2018.1.0.dist-info/RECORD
fenics_fiat-2018.1.0.dist-info/WHEEL
fenics_fiat-2018.1.0.dist-info/top_level.txt
