Metadata-Version: 2.1
Name: fenics-fiat
Version: 2018.1.0
Summary: FInite element Automatic Tabulator
Home-page: https://bitbucket.org/fenics-project/fiat/
Author: Robert C. Kirby et al.
Author-email: fenics-dev@googlegroups.com
License: LGPL v3 or later
Download-URL: https://bitbucket.org/fenics-project/fiat/downloads/fenics-fiat-2018.1.0.tar.gz
Platform: UNKNOWN
Requires-Dist: numpy
Requires-Dist: sympy
